blackdark_netcup/__init__.py
blackdark_netcup/_utilities.py
blackdark_netcup/dns_record.py
blackdark_netcup/provider.py
blackdark_netcup/pulumi-plugin.json
blackdark_netcup/py.typed
blackdark_netcup/config/__init__.py
blackdark_netcup/config/__init__.pyi
blackdark_netcup/config/vars.py
blackdark_netcup-0.1.0.dist-info/METADATA
blackdark_netcup-0.1.0.dist-info/WHEEL
blackdark_netcup-0.1.0.dist-info/top_level.txt
blackdark_netcup-0.1.0.dist-info/RECORD
