Metadata-Version: 2.4
Name: blackdark_netcup
Version: 0.1.0
Summary: A Pulumi provider for managing Netcup DNS records and resources.
Project-URL: Homepage, https://github.com/blackdark/pulumi-netcup
Requires-Python: >=3.9
Requires-Dist: parver>=0.2.1
Requires-Dist: pulumi<4.0.0,>=3.165.0
Requires-Dist: semver>=2.8.1
Requires-Dist: typing-extensions<5,>=4.11; python_version < "3.11"
